{
  "entities": [
    {
      "place": "Genesys Cloud 1",
      "position": "Software Engineer Intern 1",
      "start": "May 2023",
      "end": "Present",
      "description": ["task 1", "task 2", "task 3"]
    },
    {
      "place": "Genesys Cloud 2",
      "position": "Software Engineer Intern 2",
      "start": "May 2023",
      "end": "Present",
      "description": [
        "Lorem ipsum dolor sit amet, consectetur adipiscing elit. Etiam in consequat nisl. Integer at sapien.",
        "Lorem ipsum dolor sit amet, consectetur adipiscing elit. Etiam in consequat nisl. Integer at sapien.",
        "Lorem ipsum dolor sit amet, consectetur adipiscing elit. Etiam in consequat nisl. Integer at sapien."
      ]
    },
    {
      "place": "Genesys Cloud 3",
      "position": "Software Engineer Intern 3",
      "start": "May 2023",
      "end": "Present",
      "description": [
        "Lorem ipsum dolor sit amet, consectetur adipiscing elit. Etiam in consequat nisl. Integer at sapien.",
        "Lorem ipsum dolor sit amet, consectetur adipiscing elit. Etiam in consequat nisl. Integer at sapien.",
        "Lorem ipsum dolor sit amet, consectetur adipiscing elit. Etiam in consequat nisl. Integer at sapien."
      ]
    },
    {
      "place": "Genesys Cloud 4",
      "position": "Software Engineer Intern 4",
      "start": "May 2023",
      "end": "Present",
      "description": ["task 1", "task 2", "task 3"]
    },
    {
      "place": "Genesys Cloud 5",
      "position": "Software Engineer Intern 5",
      "start": "May 2023",
      "end": "Present",
      "description": ["task 1", "task 2", "task 3"]
    },
    {
      "place": "Genesys Cloud 6",
      "position": "Software Engineer Intern 6",
      "start": "May 2023",
      "end": "Present",
      "description": [
        "Lorem ipsum dolor sit amet, consectetur adipiscing elit. Etiam in consequat nisl. Integer at sapien.",
        "Lorem ipsum dolor sit amet, consectetur adipiscing elit. Etiam in consequat nisl. Integer at sapien.",
        "Lorem ipsum dolor sit amet, consectetur adipiscing elit. Etiam in consequat nisl. Integer at sapien."
      ]
    }
  ]
}
